LICENSE.txt
README.md
setup.cfg
setup.py
pyopensprinkler/__init__.py
pyopensprinkler/const.py
pyopensprinkler/program.py
pyopensprinkler/station.py
pyopensprinkler.egg-info/PKG-INFO
pyopensprinkler.egg-info/SOURCES.txt
pyopensprinkler.egg-info/dependency_links.txt
pyopensprinkler.egg-info/requires.txt
pyopensprinkler.egg-info/top_level.txt