Metadata-Version: 2.1
Name: pyopensprinkler
Version: 0.7.15
Summary: A Python module for the OpenSprinkler API.
Home-page: https://github.com/vinteo/py-opensprinkler
Author: Vincent Teo, Travis Glenn Hansen
Author-email: vinteo@gmail.com, travisghansen@yahoo.com
License: MIT
Download-URL: https://github.com/vinteo/py-opensprinkler/archive/0.7.15.tar.gz
Project-URL: Bug Reports, https://github.com/vinteo/py-opensprinkler/issues
Platform: Cross Platform
License-File: LICENSE.txt
